README.md
setup.py
Extra_Log_Module.egg-info/PKG-INFO
Extra_Log_Module.egg-info/SOURCES.txt
Extra_Log_Module.egg-info/dependency_links.txt
Extra_Log_Module.egg-info/requires.txt
Extra_Log_Module.egg-info/top_level.txt
log/__init__.py
log/log_module.py