Metadata-Version: 2.1
Name: Extra-Log-Module
Version: 0.0.1
Summary: Python logging module wrapper with extra detail.
Home-page: https://gitlab.com/helpdesk.landsaf/log_module
Author: Ricardo Capote
Maintainer: Sara Luis
Maintainer-email: sm.luis16@gmail.com
License: APL 2
Requires-Dist: pyyaml
